spec_checker/__init__.py
spec_checker/cli.py
spec_checker/core.py
spec_checker/dummy.py
spec_checker/html_report.py
spec_checker/parser.py
spec_checker/validator.py
specaudit-0.1.1.dist-info/METADATA
specaudit-0.1.1.dist-info/WHEEL
specaudit-0.1.1.dist-info/top_level.txt
specaudit-0.1.1.dist-info/RECORD
