Metadata-Version: 2.4
Name: specaudit
Version: 0.1.1
Summary: A universal spec validator for electronics via CLI or Streamlit UI.
Home-page: https://github.com/Yuvi369/Spec-Checker
Author: Yuvaraj
Author-email: Yuvaraj S S <your-email@example.com>
License: MIT
Keywords: validation,electronics,cli,streamlit
Classifier: Programming Language :: Python :: 3
Classifier: License :: OSI Approved :: MIT License
Classifier: Operating System :: OS Independent
Requires-Python: >=3.6
Dynamic: author
Dynamic: home-page
Dynamic: requires-python
